CHANGELOG.md
MANIFEST.in
README.md
setup.py
PySpecLines/__init__.py
PySpecLines/_version.py
PySpecLines/command_line.py
PySpecLines/compute_fluxes_and_EWs.py
PySpecLines/files/emission_lines_EWs_config.json
PySpecLines/files/emission_lines_UV.json
PySpecLines/files/emission_lines_optical.json
PySpecLines/files/dustmaps/bh/bh.h5
PySpecLines/files/dustmaps/bh/rednorth.ascii
PySpecLines/files/dustmaps/bh/redsouth.ascii
pyspeclines.egg-info/PKG-INFO
pyspeclines.egg-info/SOURCES.txt
pyspeclines.egg-info/dependency_links.txt
pyspeclines.egg-info/entry_points.txt
pyspeclines.egg-info/requires.txt
pyspeclines.egg-info/top_level.txt