Metadata-Version: 1.1
Name: pyspeclines
Version: 0.2.1
Summary: Package to compute integrated line fluxes and equivalent widths from galaxy spectra
Home-page: https://github.com/jacopo-chevallard/PySpecLines
Author: Jacopo Chevallard
Author-email: jacopo.chevallard@mailfence.com
License: MIT
Keywords: astronomy galaxies statistics visualization
Platform: UNKNOWN
Classifier: Development Status :: 3 - Alpha
Classifier: Intended Audience :: Science/Research
Classifier: Topic :: Scientific/Engineering :: Astronomy
Classifier: License :: OSI Approved :: MIT License
Classifier: Programming Language :: Python :: 2.7
